mossnet/MossNet.py
mossnet/__init__.py
mossnet/build.py
mossnet-0.0.17.dist-info/LICENSE
mossnet-0.0.17.dist-info/METADATA
mossnet-0.0.17.dist-info/WHEEL
mossnet-0.0.17.dist-info/top_level.txt
mossnet-0.0.17.dist-info/RECORD
