Metadata-Version: 2.1
Name: mossnet
Version: 0.0.17
Summary: A Python package for performing network analyses on MOSS results
Home-page: https://github.com/niemasd/MossNet
Author: Niema Moshiri
Author-email: niemamoshiri@gmail.com
Project-URL: Bug Reports, https://github.com/niemasd/MossNet/issues
Project-URL: Source, https://github.com/niemasd/MossNet
Keywords: education moss plagiarism coding programming
Classifier: Development Status :: 3 - Alpha
Classifier: Intended Audience :: Developers
Classifier: Topic :: Software Development :: Build Tools
Classifier: License :: OSI Approved :: GNU General Public License v3 or later (GPLv3+)
Classifier: Programming Language :: Python :: 3
Classifier: Programming Language :: Python :: 3.4
Classifier: Programming Language :: Python :: 3.5
Classifier: Programming Language :: Python :: 3.6
License-File: LICENSE
Requires-Dist: bs4
Requires-Dist: lxml
Requires-Dist: networkx
Provides-Extra: dev
Requires-Dist: check-manifest ; extra == 'dev'
